bdo_empire/__init__.py
bdo_empire/data_store.py
bdo_empire/generate_graph_data.py
bdo_empire/generate_reference_data.py
bdo_empire/generate_value_data.py
bdo_empire/generate_workerman_data.py
bdo_empire/main.py
bdo_empire/optimize_highspy.py
bdo_empire/solver_highspy.py
bdo_empire/data/Regioninfo.csv
bdo_empire/data/all_lodging_storage.json
bdo_empire/data/distances_tk2pzk.json
bdo_empire/data/exploration.json
bdo_empire/data/explore.csv
bdo_empire/data/node_values_per_town.json
bdo_empire/data/plantzone_drops.json
bdo_empire/data/region_workers.json
bdo_empire/data/skills.json
bdo_empire/data/values_hash.txt
bdo_empire/data/worker_static.json
bdo_empire-0.4.4.dist-info/METADATA
bdo_empire-0.4.4.dist-info/WHEEL
bdo_empire-0.4.4.dist-info/entry_points.txt
bdo_empire-0.4.4.dist-info/top_level.txt
bdo_empire-0.4.4.dist-info/RECORD
