Metadata-Version: 2.4
Name: bdo-empire
Version: 0.4.4
Summary: Worker empire optimizer for BDO using HiGHS mip solver.
Author-email: Thell 'Bo' Fowler <thell@tbfowler.net>
License-Expression: Unlicense
Requires-Python: >=3.12
Requires-Dist: certifi>=2025.8.3
Requires-Dist: CTkToolTip>=0.8
Requires-Dist: customtkinter>=5.2.2
Requires-Dist: highspy>=1.11.0
Requires-Dist: natsort>=8.4.0
Requires-Dist: networkx>=3.5
Requires-Dist: psutil>=7.0.0
Requires-Dist: tabulate>=0.9.0
